verilog/hardware/processor/iverilog/insmem/instruction_mem.v
/*
	Authored 2018-2019, Ryan Voo.

	All rights reserved.
	Redistribution and use in source and binary forms, with or without
	modification, are permitted provided that the following conditions
	are met:

	*	Redistributions of source code must retain the above
		copyright notice, this list of conditions and the following
		disclaimer.

	*	Redistributions in binary form must reproduce the above
		copyright notice, this list of conditions and the following
		disclaimer in the documentation and/or other materials
		provided with the distribution.

	*	Neither the name of the author nor the names of its
		contributors may be used to endorse or promote products
		derived from this software without specific prior written
		permission.

	THIS SOFTWARE IS PROVIDED BY THE COPYRIGHT HOLDERS AND CONTRIBUTORS
	"AS IS" AND ANY EXPRESS OR IMPLIED WARRANTIES, INCLUDING, BUT NOT
	LIMITED TO, THE IMPLIED WARRANTIES OF MERCHANTABILITY AND FITNESS
	FOR A PARTICULAR PURPOSE ARE DISCLAIMED. IN NO EVENT SHALL THE
	COPYRIGHT OWNER OR CONTRIBUTORS BE LIABLE FOR ANY DIRECT, INDIRECT,
	INCIDENTAL, SPECIAL, EXEMPLARY, OR CONSEQUENTIAL DAMAGES (INCLUDING,
	BUT NOT LIMITED TO, PROCUREMENT OF SUBSTITUTE GOODS OR SERVICES;
	LOSS OF USE, DATA, OR PROFITS; OR BUSINESS INTERRUPTION) HOWEVER
	CAUSED AND ON ANY THEORY OF LIABILITY, WHETHER IN CONTRACT, STRICT
	LIABILITY, OR TORT (INCLUDING NEGLIGENCE OR OTHERWISE) ARISING IN
	ANY WAY OUT OF THE USE OF THIS SOFTWARE, EVEN IF ADVISED OF THE
	POSSIBILITY OF SUCH DAMAGE.
*/



/*
 *	RISC-V instruction memory
 */

`include "/home/students/mec77/team3-f-of-e-tools/verilog/hardware/processor/sail-core/include/mods_to_use.v"

`ifdef USE_INSTRUCTION_MEM_BRAM

module instruction_memory_bram(addr, out, clk);
	input clk;
	reg new_read; 			//1 if new address in the line, 0 otherwise
	reg[31:0] addr_buf;
	input [31:0]		addr;
	output reg [31:0]		out;

	reg [31:0]		insmem[0:1023];
	
	initial begin
		$readmemh("/home/students/mec77/team3-f-of-e-tools/verilog/hardware/processor/verilog/program.hex",insmem);
	end
	
	always @(addr) begin
		new_read = 1'b1;
		addr_buf <= addr;
	end

	always @(negedge clk) begin
		if (new_read==1'b1) begin
			out <= insmem[addr_buf >> 2];
			new_read <= 1'b0;
		end
	end
endmodule

`else

module instruction_memory(addr, out);
	input [31:0]		addr;
	output [31:0]		out;

	reg [31:0]		instruction_memory[0:2**12-1];

	initial begin
		$readmemh("/home/students/mec77/team3-f-of-e-tools/verilog/hardware/processor/programs/program.hex",instruction_memory);
	end

	assign out = instruction_memory[addr >> 2];
endmodule

`endif

verilog/hardware/processor/iverilog/insmem/braminsmem_sim.v
module top();
	reg clk = 0;

	reg[31:0] addr;
	wire[31:0] out;

	instruction_memory_bram insmem(
		.clk(clk),
		.addr(addr),
		.out(out)
	);


//simulation
always
 #0.5 clk = ~clk;

initial begin
	$dumpfile ("braminsmem.vcd");
 	$dumpvars;

 	//reg[31:0] A, B;
 	//reg[3:0] FuncCode; //bit 32 + bit 14:12
	//reg[6:0] Opcode; //bits 6:0

 	addr = 32'b0;

 	#5
 	
	addr = 32'h4;

	#5
	addr = 32'h8;

	#5
	addr = 32'hc;

	#5
	addr = 32'h10;

	#5
	addr = 32'h14;

	#5

 	$finish;
end

endmodule

verilog/hardware/processor/iverilog/insmem/braminsmem.vcd
$date
	Thu May 27 17:53:43 2021
$end
$version
	Icarus Verilog
$end
$timescale
	1s
$end
$scope module top $end
$var wire 32 ! out [31:0] $end
$var reg 32 " addr [31:0] $end
$var reg 1 # clk $end
$scope module insmem $end
$var wire 32 $ addr [31:0] $end
$var wire 1 # clk $end
$var reg 32 % addr_buf [31:0] $end
$var reg 1 & new_read $end
$var reg 32 ' out [31:0] $end
$upscope $end
$upscope $end
$enddefinitions $end
#0
$dumpvars
bx '
1&
b0 %
b0 $
0#
b0 "
bx !
$end
#1
0&
b10011 !
b10011 '
1#
#2
0#
#3
1#
#4
0#
#5
b1000100110111 !
b1000100110111 '
b100 %
0&
1#
b100 "
b100 $
#6
0#
#7
1#
#8
0#
#9
1#
#10
b1000 %
1&
0#
b1000 "
b1000 $
#11
0&
b1000000000000010000000100010011 !
b1000000000000010000000100010011 '
1#
#12
0#
#13
1#
#14
0#
#15
b10000000000000001101111 !
b10000000000000001101111 '
b1100 %
0&
1#
b1100 "
b1100 $
#16
0#
#17
1#
#18
0#
#19
1#
#20
b10000 %
1&
0#
b10000 "
b10000 $
#21
0&
b11111110000000010000000100010011 !
b11111110000000010000000100010011 '
1#
#22
0#
#23
1#
#24
0#
#25
b100000010010111000100011 !
b100000010010111000100011 '
b10100 %
0&
1#
b10100 "
b10100 $
