verilog/hardware/processor/iverilog/adder/alu.v
/*
	Authored 2018-2019, Ryan Voo.

	All rights reserved.
	Redistribution and use in source and binary forms, with or without
	modification, are permitted provided that the following conditions
	are met:

	*	Redistributions of source code must retain the above
		copyright notice, this list of conditions and the following
		disclaimer.

	*	Redistributions in binary form must reproduce the above
		copyright notice, this list of conditions and the following
		disclaimer in the documentation and/or other materials
		provided with the distribution.

	*	Neither the name of the author nor the names of its
		contributors may be used to endorse or promote products
		derived from this software without specific prior written
		permission.

	THIS SOFTWARE IS PROVIDED BY THE COPYRIGHT HOLDERS AND CONTRIBUTORS
	"AS IS" AND ANY EXPRESS OR IMPLIED WARRANTIES, INCLUDING, BUT NOT
	LIMITED TO, THE IMPLIED WARRANTIES OF MERCHANTABILITY AND FITNESS
	FOR A PARTICULAR PURPOSE ARE DISCLAIMED. IN NO EVENT SHALL THE
	COPYRIGHT OWNER OR CONTRIBUTORS BE LIABLE FOR ANY DIRECT, INDIRECT,
	INCIDENTAL, SPECIAL, EXEMPLARY, OR CONSEQUENTIAL DAMAGES (INCLUDING,
	BUT NOT LIMITED TO, PROCUREMENT OF SUBSTITUTE GOODS OR SERVICES;
	LOSS OF USE, DATA, OR PROFITS; OR BUSINESS INTERRUPTION) HOWEVER
	CAUSED AND ON ANY THEORY OF LIABILITY, WHETHER IN CONTRACT, STRICT
	LIABILITY, OR TORT (INCLUDING NEGLIGENCE OR OTHERWISE) ARISING IN
	ANY WAY OUT OF THE USE OF THIS SOFTWARE, EVEN IF ADVISED OF THE
	POSSIBILITY OF SUCH DAMAGE.
*/



`include "../../sail-core/include/rv32i-defines.v"
`include "../../sail-core/include/sail-core-defines.v"



/*
 *	Description:
 *
 *		This module implements the ALU for the RV32I.
 */



/*
 *	Not all instructions are fed to the ALU. As a result, the ALUctl
 *	field is only unique across the instructions that are actually
 *	fed to the ALU.
 */
module alu(ALUctl, A, B, ALUOut, Branch_Enable);
	input [6:0]		ALUctl;
	input [31:0]		A;
	input [31:0]		B;
	output reg [31:0]	ALUOut;
	output reg		Branch_Enable;

	/*
	 *	This uses Yosys's support for nonzero initial values:
	 *
	 *		https://github.com/YosysHQ/yosys/commit/0793f1b196df536975a044a4ce53025c81d00c7f
	 *
	 *	Rather than using this simulation construct (`initial`),
	 *	the design should instead use a reset signal going to
	 *	modules in the design.
	 */
	initial begin
		ALUOut = 32'b0;
		Branch_Enable = 1'b0;
	end

	always @(ALUctl, A, B) begin
		case (ALUctl[3:0])
			/*
			 *	AND (the fields also match ANDI and LUI)
			 */
			`kSAIL_MICROARCHITECTURE_ALUCTL_3to0_AND:	ALUOut = A & B;

			/*
			 *	OR (the fields also match ORI)
			 */
			`kSAIL_MICROARCHITECTURE_ALUCTL_3to0_OR:	ALUOut = A | B;

			/*
			 *	ADD (the fields also match AUIPC, all loads, all stores, and ADDI)
			 */
			`kSAIL_MICROARCHITECTURE_ALUCTL_3to0_ADD:	ALUOut = A + B;

			/*
			 *	SUBTRACT (the fields also matches all branches)
			 */
			`kSAIL_MICROARCHITECTURE_ALUCTL_3to0_SUB:	ALUOut = A - B;

			/*
			 *	SLT (the fields also matches all the other SLT variants)
			 */
			`kSAIL_MICROARCHITECTURE_ALUCTL_3to0_SLT:	ALUOut = $signed(A) < $signed(B) ? 32'b1 : 32'b0;

			/*
			 *	SRL (the fields also matches the other SRL variants)
			 */
			`kSAIL_MICROARCHITECTURE_ALUCTL_3to0_SRL:	ALUOut = A >> B[4:0];

			/*
			 *	SRA (the fields also matches the other SRA variants)
			 */
			`kSAIL_MICROARCHITECTURE_ALUCTL_3to0_SRA:	ALUOut = A >>> B[4:0];

			/*
			 *	SLL (the fields also match the other SLL variants)
			 */
			`kSAIL_MICROARCHITECTURE_ALUCTL_3to0_SLL:	ALUOut = A << B[4:0];

			/*
			 *	XOR (the fields also match other XOR variants)
			 */
			`kSAIL_MICROARCHITECTURE_ALUCTL_3to0_XOR:	ALUOut = A ^ B;

			/*
			 *	CSRRW  only
			 */
			`kSAIL_MICROARCHITECTURE_ALUCTL_3to0_CSRRW:	ALUOut = A;

			/*
			 *	CSRRS only
			 */
			`kSAIL_MICROARCHITECTURE_ALUCTL_3to0_CSRRS:	ALUOut = A | B;

			/*
			 *	CSRRC only
			 */
			`kSAIL_MICROARCHITECTURE_ALUCTL_3to0_CSRRC:	ALUOut = (~A) & B;

			/*
			 *	Should never happen.
			 */
			default:					ALUOut = 0;
		endcase
	end

	always @(ALUctl, ALUOut, A, B) begin
		case (ALUctl[6:4])
			`kSAIL_MICROARCHITECTURE_ALUCTL_6to4_BEQ:	Branch_Enable = (ALUOut == 0);
			`kSAIL_MICROARCHITECTURE_ALUCTL_6to4_BNE:	Branch_Enable = !(ALUOut == 0);
			`kSAIL_MICROARCHITECTURE_ALUCTL_6to4_BLT:	Branch_Enable = ($signed(A) < $signed(B));
			`kSAIL_MICROARCHITECTURE_ALUCTL_6to4_BGE:	Branch_Enable = ($signed(A) >= $signed(B));
			`kSAIL_MICROARCHITECTURE_ALUCTL_6to4_BLTU:	Branch_Enable = ($unsigned(A) < $unsigned(B));
			`kSAIL_MICROARCHITECTURE_ALUCTL_6to4_BGEU:	Branch_Enable = ($unsigned(A) >= $unsigned(B));

			default:					Branch_Enable = 1'b0;
		endcase
	end
endmodule

verilog/hardware/processor/iverilog/adder/alu_control.v
/*
	Authored 2018-2019, Ryan Voo.

	All rights reserved.
	Redistribution and use in source and binary forms, with or without
	modification, are permitted provided that the following conditions
	are met:

	*	Redistributions of source code must retain the above
		copyright notice, this list of conditions and the following
		disclaimer.

	*	Redistributions in binary form must reproduce the above
		copyright notice, this list of conditions and the following
		disclaimer in the documentation and/or other materials
		provided with the distribution.

	*	Neither the name of the author nor the names of its
		contributors may be used to endorse or promote products
		derived from this software without specific prior written
		permission.

	THIS SOFTWARE IS PROVIDED BY THE COPYRIGHT HOLDERS AND CONTRIBUTORS
	"AS IS" AND ANY EXPRESS OR IMPLIED WARRANTIES, INCLUDING, BUT NOT
	LIMITED TO, THE IMPLIED WARRANTIES OF MERCHANTABILITY AND FITNESS
	FOR A PARTICULAR PURPOSE ARE DISCLAIMED. IN NO EVENT SHALL THE
	COPYRIGHT OWNER OR CONTRIBUTORS BE LIABLE FOR ANY DIRECT, INDIRECT,
	INCIDENTAL, SPECIAL, EXEMPLARY, OR CONSEQUENTIAL DAMAGES (INCLUDING,
	BUT NOT LIMITED TO, PROCUREMENT OF SUBSTITUTE GOODS OR SERVICES;
	LOSS OF USE, DATA, OR PROFITS; OR BUSINESS INTERRUPTION) HOWEVER
	CAUSED AND ON ANY THEORY OF LIABILITY, WHETHER IN CONTRACT, STRICT
	LIABILITY, OR TORT (INCLUDING NEGLIGENCE OR OTHERWISE) ARISING IN
	ANY WAY OUT OF THE USE OF THIS SOFTWARE, EVEN IF ADVISED OF THE
	POSSIBILITY OF SUCH DAMAGE.
*/



`include "../../sail-core/include/rv32i-defines.v"
`include "../../sail-core/include/sail-core-defines.v"



/*
 *	Description:
 *
 *		This module implements the ALU control unit
 */



module ALUControl(FuncCode, ALUCtl, Opcode);
	input [3:0]		FuncCode;
	input [6:0]		Opcode;
	output reg [6:0]	ALUCtl;

	/*
	 *	The `initial` statement below uses Yosys's support for nonzero
	 *	initial values:
	 *
	 *		https://github.com/YosysHQ/yosys/commit/0793f1b196df536975a044a4ce53025c81d00c7f
	 *
	 *	Rather than using this simulation construct (`initial`),
	 *	the design should instead use a reset signal going to
	 *	modules in the design and to thereby set the values.
	 */
	initial begin
		ALUCtl = 7'b0;
	end



	/*
	 *	TODO:
	 *
	 *	(1) Please replace the values being assigned to ALUCtl with the corresponding `defines in sail-core-defines.v
	 *	(2) Please replace the FuncCode constants with the corresponding `defines in sail-core-defines.v
	 */



	always @(*) begin
		case (Opcode)
			/*
			 *	LUI, U-Type
			 */
			`kRV32I_INSTRUCTION_OPCODE_LUI:
				ALUCtl = 7'b0000010;

			/*
			 *	AUIPC, U-Type
			 */
			`kRV32I_INSTRUCTION_OPCODE_AUIPC:
				ALUCtl = 7'b0000010;

			/*
			 *	JAL, UJ-Type
			 */
			`kRV32I_INSTRUCTION_OPCODE_JAL:
				ALUCtl = `kSAIL_MICROARCHITECTURE_ALUCTL_6to0_ILLEGAL;

			/*
			 *	JALR, I-Type
			 */
			`kRV32I_INSTRUCTION_OPCODE_JALR:
				ALUCtl = `kSAIL_MICROARCHITECTURE_ALUCTL_6to0_ILLEGAL;

			/*
			 *	Branch, SB-Type
			 */
			`kRV32I_INSTRUCTION_OPCODE_BRANCH:
				case (FuncCode[2:0])
					3'b000:
						ALUCtl = 7'b0010110; //BEQ conditions
					3'b001:
						ALUCtl = 7'b0100110; //BNE conditions
					3'b100:
						ALUCtl = 7'b0110110; //BLT conditions
					3'b101:
						ALUCtl = 7'b1000110; //BGE conditions
					3'b110:
						ALUCtl = 7'b1010110; //BLTU conditions
					3'b111:
						ALUCtl = 7'b1100110; //BGEU conditions
					default:
						ALUCtl = `kSAIL_MICROARCHITECTURE_ALUCTL_6to0_ILLEGAL;
				endcase

			/*
			 *	Loads, I-Type
			 */
			`kRV32I_INSTRUCTION_OPCODE_LOAD:
				case (FuncCode[2:0])
					3'b000:
						ALUCtl = 7'b0000010; //LB
					3'b001:
						ALUCtl = 7'b0000010; //LH
					3'b010:
						ALUCtl = 7'b0000010; //LW
					3'b100:
						ALUCtl = 7'b0000010; //LBU
					3'b101:
						ALUCtl = 7'b0000010; //LHU
					default:
						ALUCtl = `kSAIL_MICROARCHITECTURE_ALUCTL_6to0_ILLEGAL;
				endcase

			/*
			 *	Stores, S-Type
			 */
			`kRV32I_INSTRUCTION_OPCODE_STORE:
				case (FuncCode[2:0])
					3'b000:
						ALUCtl = 7'b0000010; //SB
					3'b001:
						ALUCtl = 7'b0000010; //SH
					3'b010:
						ALUCtl = 7'b0000010; //SW
					default:
						ALUCtl = `kSAIL_MICROARCHITECTURE_ALUCTL_6to0_ILLEGAL;
				endcase

			/*
			 *	Immediate operations, I-Type
			 */
			`kRV32I_INSTRUCTION_OPCODE_IMMOP:
				case (FuncCode[2:0])
					3'b000:
						ALUCtl = 7'b0000010; //ADDI
					3'b010:
						ALUCtl = 7'b0000111; //SLTI
					3'b011:
						ALUCtl = 7'b0000111; //SLTIU
					3'b100:
						ALUCtl = 7'b0001000; //XORI
					3'b110:
						ALUCtl = 7'b0000001; //ORI
					3'b111:
						ALUCtl = 7'b0000000; //ANDI
					3'b001:
						ALUCtl = 7'b0000101; //SLLI
					3'b101:
						case (FuncCode[3])
							1'b0:
								ALUCtl = 7'b0000011; //SRLI
							1'b1:
								ALUCtl = 7'b0000100; //SRAI
							default:
								ALUCtl = `kSAIL_MICROARCHITECTURE_ALUCTL_6to0_ILLEGAL;
						endcase
					default:
						ALUCtl = `kSAIL_MICROARCHITECTURE_ALUCTL_6to0_ILLEGAL;
				endcase

			/*
			 *	ADD SUB & logic shifts, R-Type
			 */
			`kRV32I_INSTRUCTION_OPCODE_ALUOP:
				case (FuncCode[2:0])
					3'b000:
						case(FuncCode[3])
							1'b0:
								ALUCtl = 7'b0000010; //ADD
							1'b1:
								ALUCtl = 7'b0000110; //SUB
							default:
								ALUCtl = `kSAIL_MICROARCHITECTURE_ALUCTL_6to0_ILLEGAL;
						endcase
					3'b001:
						ALUCtl = 7'b0000101; //SLL
					3'b010:
						ALUCtl = 7'b0000111; //SLT
					3'b011:
						ALUCtl = 7'b0000111; //SLTU
					3'b100:
						ALUCtl = 7'b0001000; //XOR
					3'b101:
						case(FuncCode[3])
							1'b0:
								ALUCtl = 7'b0000011; //SRL
							1'b1:
								ALUCtl = 7'b0000100; //SRA untested
							default:
								ALUCtl = `kSAIL_MICROARCHITECTURE_ALUCTL_6to0_ILLEGAL;
						endcase
					3'b110:
						ALUCtl = 7'b0000001; //OR
					3'b111:
						ALUCtl = 7'b0000000; //AND
					default:
						ALUCtl = `kSAIL_MICROARCHITECTURE_ALUCTL_6to0_ILLEGAL;
				endcase

			`kRV32I_INSTRUCTION_OPCODE_CSRR:
				case (FuncCode[1:0]) //use lower 2 bits of FuncCode to determine operation
					2'b01:
						ALUCtl = 7'b0001001; //CSRRW
					2'b10:
						ALUCtl = 7'b0001010; //CSRRS
					2'b11:
						ALUCtl = 7'b0001011; //CSRRC
					default:
						ALUCtl = `kSAIL_MICROARCHITECTURE_ALUCTL_6to0_ILLEGAL;
				endcase

			default:
				ALUCtl = `kSAIL_MICROARCHITECTURE_ALUCTL_6to0_ILLEGAL;
		endcase
	end
endmodule

verilog/hardware/processor/iverilog/adder/DSPalu_sim.v
module top();
	reg clk = 0;

	reg[31:0] A, B;
	wire[31:0] ALUOut;
	wire Branch_Enable;

	//alu_control interface
	reg[3:0] FuncCode;
	reg[6:0] Opcode;

	//alu aluctl interface
	wire[6:0] AluCtl_wire;

	ALUControl aluCtrl_inst(
		.FuncCode(FuncCode),
		.ALUCtl(AluCtl_wire),
		.Opcode(Opcode)
	);

	alu alu_inst(
		.ALUctl(AluCtl_wire),
		.A(A),
		.B(B),
		.ALUOut(ALUOut),
		.Branch_Enable(Branch_Enable)
	);

//simulation
always
 #0.5 clk = ~clk;

initial begin
	$dumpfile ("DSPalu.vcd");
 	$dumpvars;

 	//reg[31:0] A, B;
 	//reg[3:0] FuncCode; //bit 32 + bit 14:12
	//reg[6:0] Opcode; //bits 6:0

 	A = 32'b0;
 	B = 32'b0;
 	FuncCode = 4'b0;
 	Opcode = 7'b0;

 	#5

 	//simulate AND instruction
 	A = 32'b00001111;
 	B = 32'b01010101;
 	FuncCode = 4'b0111;
 	Opcode = 7'b0110011;

 	#5

 	//simulate OR instruction
 	A = 32'b00001111;
 	B = 32'b01010101;
 	FuncCode = 4'b0110;
 	Opcode = 7'b0110011;

 	#5

 	//simulate ADD instruction
 	A = 32'd10000;
 	B = 32'd0111;
 	FuncCode = 4'b0000;
 	Opcode = 7'b0110011;

 	#5

 	//simulate SUB instruction
 	A = 32'd10000;
 	B = 32'd0111;
 	FuncCode = 4'b1000;
 	Opcode = 7'b0110011;

 	#5

 	//simulate SLT instuction
 	A = 32'b0;
 	B = 32'b10;
 	FuncCode = 4'b0010;
 	Opcode = 7'b0110011;

 	#5

 	//simulate SRL instruction
 	A = 32'b10000;
 	B = 32'b10;
 	FuncCode = 4'b0101;
 	Opcode = 7'b0110011;

 	#5

 	//simulate SRA instruction
 	A = 32'b1000;
 	B = 32'b1;
 	FuncCode = 4'b1101;
 	Opcode = 7'b0110011;

 	#5

 	//simulate SLL instruction
 	A = 32'b10;
 	B = 32'b10;
 	FuncCode = 4'b0001;
 	Opcode = 7'b0110011;

 	#5

 	//simulate XOR instruction
 	A = 32'b01010101;
 	B = 32'b11111111;
 	FuncCode = 4'b0100;
 	Opcode = 7'b0110011;

 	#5

 	$finish;
end

endmodule

verilog/hardware/processor/iverilog/adder/alu.vcd
$date
	Tue May 25 18:29:58 2021
$end
$version
	Icarus Verilog
$end
$timescale
	1s
$end
$scope module top $end
$var wire 1 ! Branch_Enable $end
$var wire 7 " AluCtl_wire [6:0] $end
$var wire 32 # ALUOut [31:0] $end
$var reg 32 $ A [31:0] $end
$var reg 32 % B [31:0] $end
$var reg 4 & FuncCode [3:0] $end
$var reg 7 ' Opcode [6:0] $end
$var reg 1 ( clk $end
$scope module aluCtrl_inst $end
$var wire 4 ) FuncCode [3:0] $end
$var wire 7 * Opcode [6:0] $end
$var reg 7 + ALUCtl [6:0] $end
$upscope $end
$scope module alu_inst $end
$var wire 32 , A [31:0] $end
$var wire 7 - ALUctl [6:0] $end
$var wire 32 . B [31:0] $end
$var reg 32 / ALUOut [31:0] $end
$var reg 1 ! Branch_Enable $end
$upscope $end
$upscope $end
$enddefinitions $end
#0
$dumpvars
b0 /
b0 .
b1111 -
b0 ,
b1111 +
b0 *
b0 )
0(
b0 '
b0 &
b0 %
b0 $
b0 #
b1111 "
0!
$end
#1
1(
#2
0(
#3
1(
#4
0(
#5
b101 #
b101 /
b0 "
b0 +
b0 -
1(
b110011 '
b110011 *
b111 &
b111 )
b1010101 %
b1010101 .
b1111 $
b1111 ,
#6
0(
#7
1(
#8
0(
#9
1(
#10
b1011111 #
b1011111 /
b1 "
b1 +
b1 -
0(
b110 &
b110 )
#11
1(
#12
0(
#13
1(
#14
0(
#15
b10 "
b10 +
b10 -
b10011101111111 #
b10011101111111 /
1(
b0 &
b0 )
b1101111 %
b1101111 .
b10011100010000 $
b10011100010000 ,
#16
0(
#17
1(
#18
0(
#19
1(
#20
b10011010100001 #
b10011010100001 /
b110 "
b110 +
b110 -
0(
b1000 &
b1000 )
#21
1(
#22
0(
#23
1(
#24
0(
#25
b111 "
b111 +
b111 -
b1 #
b1 /
1(
b10 &
b10 )
b10 %
b10 .
b0 $
b0 ,
#26
0(
#27
1(
#28
0(
#29
1(
#30
b11 "
b11 +
b11 -
b100 #
b100 /
0(
b101 &
b101 )
b10000 $
b10000 ,
#31
1(
#32
0(
#33
1(
#34
0(
#35
b100 "
b100 +
b100 -
1(
b1101 &
b1101 )
b1 %
b1 .
b1000 $
b1000 ,
#36
0(
#37
1(
#38
0(
#39
1(
#40
b101 "
b101 +
b101 -
b1000 #
b1000 /
0(
b1 &
b1 )
b10 %
b10 .
b10 $
b10 ,
#41
1(
#42
0(
#43
1(
#44
0(
#45
b1000 "
b1000 +
b1000 -
b10101010 #
b10101010 /
1(
b100 &
b100 )
b11111111 %
b11111111 .
b1010101 $
b1010101 ,
